odoo/addons/sale_report_margin/README.rst
odoo/addons/sale_report_margin/__init__.py
odoo/addons/sale_report_margin/__manifest__.py
odoo/addons/sale_report_margin/i18n/es.po
odoo/addons/sale_report_margin/i18n/it.po
odoo/addons/sale_report_margin/i18n/sale_report_margin.pot
odoo/addons/sale_report_margin/readme/CONTRIBUTORS.md
odoo/addons/sale_report_margin/readme/DESCRIPTION.md
odoo/addons/sale_report_margin/readme/ROADMAP.md
odoo/addons/sale_report_margin/readme/USAGE.md
odoo/addons/sale_report_margin/reports/__init__.py
odoo/addons/sale_report_margin/reports/sale_report.py
odoo/addons/sale_report_margin/static/description/icon.png
odoo/addons/sale_report_margin/static/description/index.html
odoo/addons/sale_report_margin/tests/__init__.py
odoo/addons/sale_report_margin/tests/test_sale_report_margin.py
odoo_addon_sale_report_margin-18.0.1.0.0.2.dist-info/METADATA
odoo_addon_sale_report_margin-18.0.1.0.0.2.dist-info/WHEEL
odoo_addon_sale_report_margin-18.0.1.0.0.2.dist-info/top_level.txt
odoo_addon_sale_report_margin-18.0.1.0.0.2.dist-info/RECORD
